remembers/__init__.py
remembers/cache_backend.py
remembers/cache_entry.py
remembers/cache_key_builder.py
remembers/cache_stats.py
remembers/decorator.py
remembers/filesystem_backend.py
remembers/func_wrapper.py
remembers/key_path_resolver.py
remembers/lru_cache.py
remembers-0.1.0.dist-info/WHEEL
remembers-0.1.0.dist-info/METADATA
remembers-0.1.0.dist-info/RECORD
