Metadata-Version: 2.3
Name: remembers
Version: 0.1.0
Summary: A blazing-fast, async-friendly, thread-safe caching decorator for Python that just works. Drop it on any function and watch it remember results like magic.
Keywords: cache,caching,lru,decorator,async,thread-safe,persistent,ttl,memoization
Author: Marcus Figueiredo
Author-email: Marcus Figueiredo <figueiredo@protonmail.com>
License: MIT
Classifier: Development Status :: 4 - Beta
Classifier: Intended Audience :: Developers
Classifier: License :: OSI Approved :: MIT License
Classifier: Operating System :: OS Independent
Classifier: Programming Language :: Python
Classifier: Programming Language :: Python :: 3
Classifier: Programming Language :: Python :: 3.12
Classifier: Programming Language :: Python :: 3.13
Classifier: Topic :: Software Development :: Libraries :: Python Modules
Classifier: Topic :: System :: Archiving
Classifier: Typing :: Typed
Maintainer: Marcus Figueiredo
Maintainer-email: Marcus Figueiredo <figueiredo@protonmail.com>
Requires-Python: >=3.12
Project-URL: Documentation, https://github.com/jovemexausto/remembers#readme
Project-URL: Homepage, https://github.com/jovemexausto/remembers
Project-URL: Issues, https://github.com/jovemexausto/remembers/issues
Project-URL: Repository, https://github.com/jovemexausto/remembers
